{"DocumentConnection":{"type":"DocumentConnection","resolveType":"multiCollectionDocumentList","collections":["post","homePage","aboutPage","siteSettings","newsletterCTA","footer"]},"Node":{"type":"Node","resolveType":"nodeDocument"},"DocumentNode":{"type":"DocumentNode","resolveType":"multiCollectionDocument","createDocument":"create","updateDocument":"update"},"Post":{"type":"Post","resolveType":"collectionDocument","collection":"post","createPost":"create","updatePost":"update"},"PostConnection":{"type":"PostConnection","resolveType":"collectionDocumentList","collection":"post"},"HomePage":{"type":"HomePage","resolveType":"collectionDocument","collection":"homePage","createHomePage":"create","updateHomePage":"update"},"HomePageConnection":{"type":"HomePageConnection","resolveType":"collectionDocumentList","collection":"homePage"},"AboutPage":{"type":"AboutPage","resolveType":"collectionDocument","collection":"aboutPage","createAboutPage":"create","updateAboutPage":"update"},"AboutPageConnection":{"type":"AboutPageConnection","resolveType":"collectionDocumentList","collection":"aboutPage"},"SiteSettings":{"type":"SiteSettings","resolveType":"collectionDocument","collection":"siteSettings","createSiteSettings":"create","updateSiteSettings":"update"},"SiteSettingsConnection":{"type":"SiteSettingsConnection","resolveType":"collectionDocumentList","collection":"siteSettings"},"NewsletterCTA":{"type":"NewsletterCTA","resolveType":"collectionDocument","collection":"newsletterCTA","createNewsletterCTA":"create","updateNewsletterCTA":"update"},"NewsletterCTAConnection":{"type":"NewsletterCTAConnection","resolveType":"collectionDocumentList","collection":"newsletterCTA"},"Footer":{"type":"Footer","resolveType":"collectionDocument","collection":"footer","createFooter":"create","updateFooter":"update"},"FooterConnection":{"type":"FooterConnection","resolveType":"collectionDocumentList","collection":"footer"}}